mixbox/__init__.py
mixbox/binding_utils.py
mixbox/compat.py
mixbox/datautils.py
mixbox/dates.py
mixbox/entities.py
mixbox/exceptions.py
mixbox/fields.py
mixbox/idgen.py
mixbox/namespaces.py
mixbox/parser.py
mixbox/signals.py
mixbox/typedlist.py
mixbox/version.py
mixbox/xml.py
mixbox/vendor/__init__.py
mixbox/vendor/six.py
mixbox-1.0.4.dist-info/LICENSE.txt
mixbox-1.0.4.dist-info/METADATA
mixbox-1.0.4.dist-info/WHEEL
mixbox-1.0.4.dist-info/top_level.txt
mixbox-1.0.4.dist-info/RECORD
