Metadata-Version: 2.1
Name: mixbox
Version: 1.0.4
Summary: Utility library for cybox, maec, and stix packages
Home-page: http://github.com/CybOXProject/mixbox
Author: The MITRE Corporation
Author-email: cybox@mitre.org
License: UNKNOWN
Platform: UNKNOWN
Classifier: Development Status :: 5 - Production/Stable
Classifier: Intended Audience :: Developers
Classifier: License :: OSI Approved :: BSD License
Classifier: Operating System :: OS Independent
Classifier: Programming Language :: Python :: 2
Classifier: Programming Language :: Python :: 2.6
Classifier: Programming Language :: Python :: 2.7
Classifier: Programming Language :: Python :: 3
Classifier: Programming Language :: Python :: 3.5
Classifier: Programming Language :: Python :: 3.6
Classifier: Programming Language :: Python :: 3.7
Classifier: Programming Language :: Python :: 3.8
Requires-Dist: python-dateutil
Requires-Dist: ordered-set
Requires-Dist: lxml
Requires-Dist: weakrefmethod (>=1.0.3)
